lumigo_tracer/VERSION
lumigo_tracer/__init__.py
lumigo_tracer/auto_instrument_handler.py
lumigo_tracer/lumigo_utils.py
lumigo_tracer/parsing_utils.py
lumigo_tracer/user_utils.py
lumigo_tracer/w3c_context.py
lumigo_tracer/auto_tag/__init__.py
lumigo_tracer/auto_tag/auto_tag_event.py
lumigo_tracer/event/__init__.py
lumigo_tracer/event/event_dumper.py
lumigo_tracer/event/trigger_parsing/__init__.py
lumigo_tracer/event/trigger_parsing/step_function_parser.py
lumigo_tracer/extension/__init__.py
lumigo_tracer/extension/extension.py
lumigo_tracer/extension/extension_utils.py
lumigo_tracer/extension/lambda_service.py
lumigo_tracer/extension/main.py
lumigo_tracer/extension/sampler.py
lumigo_tracer/lambda_tracer/__init__.py
lumigo_tracer/lambda_tracer/global_scope_exec.py
lumigo_tracer/lambda_tracer/lambda_reporter.py
lumigo_tracer/lambda_tracer/spans_container.py
lumigo_tracer/lambda_tracer/tracer.py
lumigo_tracer/libs/__init__.py
lumigo_tracer/libs/wrapt.py
lumigo_tracer/libs/awslambdaric/__init__.py
lumigo_tracer/libs/awslambdaric/bootstrap.py
lumigo_tracer/libs/awslambdaric/lambda_runtime_exception.py
lumigo_tracer/test_module/__init__.py
lumigo_tracer/test_module/test.py
lumigo_tracer/wrappers/__init__.py
lumigo_tracer/wrappers/aiohttp/__init__.py
lumigo_tracer/wrappers/aiohttp/aiohttp_wrapper.py
lumigo_tracer/wrappers/http/__init__.py
lumigo_tracer/wrappers/http/http_data_classes.py
lumigo_tracer/wrappers/http/http_parser.py
lumigo_tracer/wrappers/http/sync_http_wrappers.py
lumigo_tracer/wrappers/pymongo/__init__.py
lumigo_tracer/wrappers/pymongo/pymongo_wrapper.py
lumigo_tracer/wrappers/redis/__init__.py
lumigo_tracer/wrappers/redis/redis_wrapper.py
lumigo_tracer/wrappers/sql/__init__.py
lumigo_tracer/wrappers/sql/sqlalchemy_wrapper.py
lumigo_tracer/wrappers/vertexai/__init__.py
lumigo_tracer/wrappers/vertexai/vertexai_wrapper.py
lumigo_tracer-1.1.257.dist-info/LICENSE
lumigo_tracer-1.1.257.dist-info/METADATA
lumigo_tracer-1.1.257.dist-info/WHEEL
lumigo_tracer-1.1.257.dist-info/top_level.txt
lumigo_tracer-1.1.257.dist-info/RECORD
