Metadata-Version: 2.1
Name: lumigo-tracer
Version: 1.1.257
Summary: Lumigo Tracer for Python v3.6 / 3.7 / 3.8 / 3.9 / 3.10 runtimes
Home-page: https://github.com/lumigo-io/python_tracer.git
Author: Lumigo LTD (https://lumigo.io)
Author-email: support@lumigo.io
License: Apache License 2.0
Platform: UNKNOWN
Classifier: Programming Language :: Python :: 3
Classifier: Operating System :: OS Independent
Requires-Dist: lumigo-core (==0.0.16)
